{
  "generated_at_utc": "2026-07-20T11:12:47Z",
  "dataset": "so_tasa_aceptacion",
  "source_mode": "history",
  "snapshot_count": 2,
  "latest_snapshot_date": "2026-07-20",
  "previous_snapshot_date": "2026-07-13",
  "has_historical_comparison": true,
  "item_count": 5,
  "summary": {
    "raw_leader": {
      "tecnologia": "svelte",
      "total_preguntas": 62,
      "respuestas_aceptadas": 21,
      "tasa_aceptacion_pct": 33.87,
      "total_preguntas_prev": 63,
      "respuestas_aceptadas_prev": 22,
      "tasa_aceptacion_prev_pct": 34.92,
      "delta_tasa_pct": -1.05,
      "delta_preguntas": -1,
      "sample_bucket": "baja",
      "confidence_score": 0.233415,
      "raw_rank": 1,
      "confidence_rank": 2
    },
    "confidence_leader": {
      "tecnologia": "angular",
      "total_preguntas": 735,
      "respuestas_aceptadas": 215,
      "tasa_aceptacion_pct": 29.25,
      "total_preguntas_prev": 756,
      "respuestas_aceptadas_prev": 220,
      "tasa_aceptacion_prev_pct": 29.1,
      "delta_tasa_pct": 0.15,
      "delta_preguntas": -21,
      "sample_bucket": "media",
      "confidence_score": 0.260775,
      "raw_rank": 2,
      "confidence_rank": 1
    },
    "highest_improvement": {
      "tecnologia": "reactjs",
      "total_preguntas": 792,
      "respuestas_aceptadas": 192,
      "tasa_aceptacion_pct": 24.24,
      "total_preguntas_prev": 846,
      "respuestas_aceptadas_prev": 203,
      "tasa_aceptacion_prev_pct": 24.0,
      "delta_tasa_pct": 0.24,
      "delta_preguntas": -54,
      "sample_bucket": "media",
      "confidence_score": 0.213867,
      "raw_rank": 4,
      "confidence_rank": 3
    },
    "largest_drop": {
      "tecnologia": "svelte",
      "total_preguntas": 62,
      "respuestas_aceptadas": 21,
      "tasa_aceptacion_pct": 33.87,
      "total_preguntas_prev": 63,
      "respuestas_aceptadas_prev": 22,
      "tasa_aceptacion_prev_pct": 34.92,
      "delta_tasa_pct": -1.05,
      "delta_preguntas": -1,
      "sample_bucket": "baja",
      "confidence_score": 0.233415,
      "raw_rank": 1,
      "confidence_rank": 2
    },
    "largest_sample": {
      "tecnologia": "reactjs",
      "total_preguntas": 792,
      "respuestas_aceptadas": 192,
      "tasa_aceptacion_pct": 24.24,
      "total_preguntas_prev": 846,
      "respuestas_aceptadas_prev": 203,
      "tasa_aceptacion_prev_pct": 24.0,
      "delta_tasa_pct": 0.24,
      "delta_preguntas": -54,
      "sample_bucket": "media",
      "confidence_score": 0.213867,
      "raw_rank": 4,
      "confidence_rank": 3
    }
  },
  "latest_items": [
    {
      "tecnologia": "svelte",
      "total_preguntas": 62,
      "respuestas_aceptadas": 21,
      "tasa_aceptacion_pct": 33.87,
      "total_preguntas_prev": 63,
      "respuestas_aceptadas_prev": 22,
      "tasa_aceptacion_prev_pct": 34.92,
      "delta_tasa_pct": -1.05,
      "delta_preguntas": -1,
      "sample_bucket": "baja",
      "confidence_score": 0.233415,
      "raw_rank": 1,
      "confidence_rank": 2
    },
    {
      "tecnologia": "angular",
      "total_preguntas": 735,
      "respuestas_aceptadas": 215,
      "tasa_aceptacion_pct": 29.25,
      "total_preguntas_prev": 756,
      "respuestas_aceptadas_prev": 220,
      "tasa_aceptacion_prev_pct": 29.1,
      "delta_tasa_pct": 0.15,
      "delta_preguntas": -21,
      "sample_bucket": "media",
      "confidence_score": 0.260775,
      "raw_rank": 2,
      "confidence_rank": 1
    },
    {
      "tecnologia": "vue.js",
      "total_preguntas": 183,
      "respuestas_aceptadas": 47,
      "tasa_aceptacion_pct": 25.68,
      "total_preguntas_prev": 193,
      "respuestas_aceptadas_prev": 50,
      "tasa_aceptacion_prev_pct": 25.91,
      "delta_tasa_pct": -0.23,
      "delta_preguntas": -10,
      "sample_bucket": "baja",
      "confidence_score": 0.198986,
      "raw_rank": 3,
      "confidence_rank": 4
    },
    {
      "tecnologia": "reactjs",
      "total_preguntas": 792,
      "respuestas_aceptadas": 192,
      "tasa_aceptacion_pct": 24.24,
      "total_preguntas_prev": 846,
      "respuestas_aceptadas_prev": 203,
      "tasa_aceptacion_prev_pct": 24.0,
      "delta_tasa_pct": 0.24,
      "delta_preguntas": -54,
      "sample_bucket": "media",
      "confidence_score": 0.213867,
      "raw_rank": 4,
      "confidence_rank": 3
    },
    {
      "tecnologia": "next.js",
      "total_preguntas": 505,
      "respuestas_aceptadas": 83,
      "tasa_aceptacion_pct": 16.44,
      "total_preguntas_prev": 534,
      "respuestas_aceptadas_prev": 90,
      "tasa_aceptacion_prev_pct": 16.85,
      "delta_tasa_pct": -0.41,
      "delta_preguntas": -29,
      "sample_bucket": "media",
      "confidence_score": 0.13459,
      "raw_rank": 5,
      "confidence_rank": 5
    }
  ],
  "snapshots": [
    {
      "date": "2026-07-13",
      "path": "datos/history/so_aceptacion/year=2026/month=07/day=13/so_tasa_aceptacion.csv",
      "source_type": "history",
      "row_count": 5,
      "item_count": 5,
      "items": [
        {
          "tecnologia": "svelte",
          "total_preguntas": 63,
          "respuestas_aceptadas": 22,
          "tasa_aceptacion_pct": 34.92,
          "sample_bucket": "baja",
          "confidence_score": 0.243258,
          "raw_rank": 1,
          "confidence_rank": 2
        },
        {
          "tecnologia": "angular",
          "total_preguntas": 756,
          "respuestas_aceptadas": 220,
          "tasa_aceptacion_pct": 29.1,
          "sample_bucket": "media",
          "confidence_score": 0.259747,
          "raw_rank": 2,
          "confidence_rank": 1
        },
        {
          "tecnologia": "vue.js",
          "total_preguntas": 193,
          "respuestas_aceptadas": 50,
          "tasa_aceptacion_pct": 25.91,
          "sample_bucket": "baja",
          "confidence_score": 0.202383,
          "raw_rank": 3,
          "confidence_rank": 4
        },
        {
          "tecnologia": "reactjs",
          "total_preguntas": 846,
          "respuestas_aceptadas": 203,
          "tasa_aceptacion_pct": 24.0,
          "sample_bucket": "media",
          "confidence_score": 0.212392,
          "raw_rank": 4,
          "confidence_rank": 3
        },
        {
          "tecnologia": "next.js",
          "total_preguntas": 534,
          "respuestas_aceptadas": 90,
          "tasa_aceptacion_pct": 16.85,
          "sample_bucket": "media",
          "confidence_score": 0.139181,
          "raw_rank": 5,
          "confidence_rank": 5
        }
      ]
    },
    {
      "date": "2026-07-20",
      "path": "datos/history/so_aceptacion/year=2026/month=07/day=20/so_tasa_aceptacion.csv",
      "source_type": "history",
      "row_count": 5,
      "item_count": 5,
      "items": [
        {
          "tecnologia": "svelte",
          "total_preguntas": 62,
          "respuestas_aceptadas": 21,
          "tasa_aceptacion_pct": 33.87,
          "sample_bucket": "baja",
          "confidence_score": 0.233415,
          "raw_rank": 1,
          "confidence_rank": 2
        },
        {
          "tecnologia": "angular",
          "total_preguntas": 735,
          "respuestas_aceptadas": 215,
          "tasa_aceptacion_pct": 29.25,
          "sample_bucket": "media",
          "confidence_score": 0.260775,
          "raw_rank": 2,
          "confidence_rank": 1
        },
        {
          "tecnologia": "vue.js",
          "total_preguntas": 183,
          "respuestas_aceptadas": 47,
          "tasa_aceptacion_pct": 25.68,
          "sample_bucket": "baja",
          "confidence_score": 0.198986,
          "raw_rank": 3,
          "confidence_rank": 4
        },
        {
          "tecnologia": "reactjs",
          "total_preguntas": 792,
          "respuestas_aceptadas": 192,
          "tasa_aceptacion_pct": 24.24,
          "sample_bucket": "media",
          "confidence_score": 0.213867,
          "raw_rank": 4,
          "confidence_rank": 3
        },
        {
          "tecnologia": "next.js",
          "total_preguntas": 505,
          "respuestas_aceptadas": 83,
          "tasa_aceptacion_pct": 16.44,
          "sample_bucket": "media",
          "confidence_score": 0.13459,
          "raw_rank": 5,
          "confidence_rank": 5
        }
      ]
    }
  ]
}