{
  "generated_at_utc": "2026-04-06T09:18:10Z",
  "snapshot_count": 2,
  "snapshots": [
    {
      "date": "2026-03-30",
      "path": "datos/history/trend_score/year=2026/month=03/day=30/trend_score.csv",
      "source_type": "history",
      "row_count": 22,
      "top_10": [
        {
          "ranking": 1,
          "tecnologia": "Python",
          "slug": "python",
          "github_score": 100.0,
          "so_score": 100.0,
          "reddit_score": 13.16,
          "trend_score": 78.29,
          "fuentes": 3,
          "available_source_codes": [
            "GH",
            "SO",
            "RD"
          ],
          "score_prev": 78.15,
          "delta_score": 0.14,
          "ranking_prev": 1,
          "delta_ranking": 0
        },
        {
          "ranking": 2,
          "tecnologia": "TypeScript",
          "slug": "typescript",
          "github_score": 82.52,
          "so_score": 18.95,
          "reddit_score": 13.82,
          "trend_score": 43.1,
          "fuentes": 3,
          "available_source_codes": [
            "GH",
            "SO",
            "RD"
          ],
          "score_prev": 43.32,
          "delta_score": -0.22,
          "ranking_prev": 2,
          "delta_ranking": 0
        },
        {
          "ranking": 3,
          "tecnologia": "AI/ML",
          "slug": "ai-ml",
          "github_score": 0.0,
          "so_score": 0.0,
          "reddit_score": 100.0,
          "trend_score": 25.0,
          "fuentes": 1,
          "available_source_codes": [
            "RD"
          ],
          "score_prev": 25.0,
          "delta_score": 0.0,
          "ranking_prev": 3,
          "delta_ranking": 0
        },
        {
          "ranking": 4,
          "tecnologia": "JavaScript",
          "slug": "javascript",
          "github_score": 19.42,
          "so_score": 41.79,
          "reddit_score": 0.0,
          "trend_score": 22.39,
          "fuentes": 2,
          "available_source_codes": [
            "GH",
            "SO"
          ],
          "score_prev": 22.03,
          "delta_score": 0.36,
          "ranking_prev": 4,
          "delta_ranking": 0
        },
        {
          "ranking": 5,
          "tecnologia": "Java",
          "slug": "java",
          "github_score": 2.27,
          "so_score": 41.76,
          "reddit_score": 0.0,
          "trend_score": 15.52,
          "fuentes": 2,
          "available_source_codes": [
            "GH",
            "SO"
          ],
          "score_prev": 15.39,
          "delta_score": 0.13,
          "ranking_prev": 5,
          "delta_ranking": 0
        },
        {
          "ranking": 6,
          "tecnologia": "C#",
          "slug": "c-sharp",
          "github_score": 1.62,
          "so_score": 40.66,
          "reddit_score": 0.0,
          "trend_score": 14.88,
          "fuentes": 2,
          "available_source_codes": [
            "GH",
            "SO"
          ],
          "score_prev": 14.9,
          "delta_score": -0.02,
          "ranking_prev": 6,
          "delta_ranking": 0
        },
        {
          "ranking": 7,
          "tecnologia": "C++",
          "slug": "c-plus-plus",
          "github_score": 4.53,
          "so_score": 35.3,
          "reddit_score": 0.0,
          "trend_score": 14.17,
          "fuentes": 2,
          "available_source_codes": [
            "GH",
            "SO"
          ],
          "score_prev": 14.31,
          "delta_score": -0.14,
          "ranking_prev": 7,
          "delta_ranking": 0
        },
        {
          "ranking": 8,
          "tecnologia": "Go",
          "slug": "go",
          "github_score": 15.21,
          "so_score": 2.47,
          "reddit_score": 0.0,
          "trend_score": 6.95,
          "fuentes": 2,
          "available_source_codes": [
            "GH",
            "SO"
          ],
          "score_prev": 6.94,
          "delta_score": 0.01,
          "ranking_prev": 8,
          "delta_ranking": 0
        },
        {
          "ranking": 9,
          "tecnologia": "Performance",
          "slug": "performance",
          "github_score": 0.0,
          "so_score": 0.0,
          "reddit_score": 26.32,
          "trend_score": 6.58,
          "fuentes": 1,
          "available_source_codes": [
            "RD"
          ],
          "score_prev": 6.64,
          "delta_score": -0.06,
          "ranking_prev": 9,
          "delta_ranking": 0
        },
        {
          "ranking": 10,
          "tecnologia": "Security",
          "slug": "security",
          "github_score": 0.0,
          "so_score": 0.0,
          "reddit_score": 25.0,
          "trend_score": 6.25,
          "fuentes": 1,
          "available_source_codes": [
            "RD"
          ],
          "score_prev": 6.47,
          "delta_score": -0.22,
          "ranking_prev": 10,
          "delta_ranking": 0
        }
      ]
    },
    {
      "date": "2026-04-06",
      "path": "datos/history/trend_score/year=2026/month=04/day=06/trend_score.csv",
      "source_type": "history",
      "row_count": 21,
      "top_10": [
        {
          "ranking": 1,
          "tecnologia": "Python",
          "slug": "python",
          "github_score": 100.0,
          "so_score": 100.0,
          "reddit_score": 4.38,
          "trend_score": 76.1,
          "fuentes": 3,
          "available_source_codes": [
            "GH",
            "SO",
            "RD"
          ],
          "score_prev": 78.29,
          "delta_score": -2.19,
          "ranking_prev": 1,
          "delta_ranking": 0
        },
        {
          "ranking": 2,
          "tecnologia": "TypeScript",
          "slug": "typescript",
          "github_score": 85.34,
          "so_score": 18.7,
          "reddit_score": 9.49,
          "trend_score": 43.05,
          "fuentes": 3,
          "available_source_codes": [
            "GH",
            "SO",
            "RD"
          ],
          "score_prev": 43.1,
          "delta_score": -0.05,
          "ranking_prev": 2,
          "delta_ranking": 0
        },
        {
          "ranking": 3,
          "tecnologia": "AI/ML",
          "slug": "ai-ml",
          "github_score": 0.0,
          "so_score": 0.0,
          "reddit_score": 100.0,
          "trend_score": 25.0,
          "fuentes": 1,
          "available_source_codes": [
            "RD"
          ],
          "score_prev": 25.0,
          "delta_score": 0.0,
          "ranking_prev": 3,
          "delta_ranking": 0
        },
        {
          "ranking": 4,
          "tecnologia": "JavaScript",
          "slug": "javascript",
          "github_score": 19.54,
          "so_score": 41.5,
          "reddit_score": 0.0,
          "trend_score": 22.34,
          "fuentes": 2,
          "available_source_codes": [
            "GH",
            "SO"
          ],
          "score_prev": 22.39,
          "delta_score": -0.05,
          "ranking_prev": 4,
          "delta_ranking": 0
        },
        {
          "ranking": 5,
          "tecnologia": "Java",
          "slug": "java",
          "github_score": 2.28,
          "so_score": 41.42,
          "reddit_score": 0.0,
          "trend_score": 15.41,
          "fuentes": 2,
          "available_source_codes": [
            "GH",
            "SO"
          ],
          "score_prev": 15.52,
          "delta_score": -0.11,
          "ranking_prev": 5,
          "delta_ranking": 0
        },
        {
          "ranking": 6,
          "tecnologia": "C#",
          "slug": "c-sharp",
          "github_score": 1.95,
          "so_score": 40.7,
          "reddit_score": 0.0,
          "trend_score": 15.02,
          "fuentes": 2,
          "available_source_codes": [
            "GH",
            "SO"
          ],
          "score_prev": 14.88,
          "delta_score": 0.14,
          "ranking_prev": 6,
          "delta_ranking": 0
        },
        {
          "ranking": 7,
          "tecnologia": "C++",
          "slug": "c-plus-plus",
          "github_score": 4.89,
          "so_score": 35.69,
          "reddit_score": 0.0,
          "trend_score": 14.45,
          "fuentes": 2,
          "available_source_codes": [
            "GH",
            "SO"
          ],
          "score_prev": 14.17,
          "delta_score": 0.28,
          "ranking_prev": 7,
          "delta_ranking": 0
        },
        {
          "ranking": 8,
          "tecnologia": "Performance",
          "slug": "performance",
          "github_score": 0.0,
          "so_score": 0.0,
          "reddit_score": 32.85,
          "trend_score": 8.21,
          "fuentes": 1,
          "available_source_codes": [
            "RD"
          ],
          "score_prev": 6.58,
          "delta_score": 1.63,
          "ranking_prev": 9,
          "delta_ranking": 1
        },
        {
          "ranking": 9,
          "tecnologia": "Go",
          "slug": "go",
          "github_score": 16.29,
          "so_score": 2.51,
          "reddit_score": 0.0,
          "trend_score": 7.39,
          "fuentes": 2,
          "available_source_codes": [
            "GH",
            "SO"
          ],
          "score_prev": 6.95,
          "delta_score": 0.44,
          "ranking_prev": 8,
          "delta_ranking": -1
        },
        {
          "ranking": 10,
          "tecnologia": "Security",
          "slug": "security",
          "github_score": 0.0,
          "so_score": 0.0,
          "reddit_score": 26.28,
          "trend_score": 6.57,
          "fuentes": 1,
          "available_source_codes": [
            "RD"
          ],
          "score_prev": 6.25,
          "delta_score": 0.32,
          "ranking_prev": 10,
          "delta_ranking": 0
        }
      ]
    }
  ],
  "series": [
    {
      "tecnologia": "Python",
      "slug": "python",
      "points": [
        {
          "date": "2026-03-30",
          "ranking": 1,
          "github_score": 100.0,
          "so_score": 100.0,
          "reddit_score": 13.16,
          "trend_score": 78.29,
          "fuentes": 3,
          "available_source_codes": [
            "GH",
            "SO",
            "RD"
          ]
        },
        {
          "date": "2026-04-06",
          "ranking": 1,
          "github_score": 100.0,
          "so_score": 100.0,
          "reddit_score": 4.38,
          "trend_score": 76.1,
          "fuentes": 3,
          "available_source_codes": [
            "GH",
            "SO",
            "RD"
          ]
        }
      ]
    },
    {
      "tecnologia": "TypeScript",
      "slug": "typescript",
      "points": [
        {
          "date": "2026-03-30",
          "ranking": 2,
          "github_score": 82.52,
          "so_score": 18.95,
          "reddit_score": 13.82,
          "trend_score": 43.1,
          "fuentes": 3,
          "available_source_codes": [
            "GH",
            "SO",
            "RD"
          ]
        },
        {
          "date": "2026-04-06",
          "ranking": 2,
          "github_score": 85.34,
          "so_score": 18.7,
          "reddit_score": 9.49,
          "trend_score": 43.05,
          "fuentes": 3,
          "available_source_codes": [
            "GH",
            "SO",
            "RD"
          ]
        }
      ]
    },
    {
      "tecnologia": "AI/ML",
      "slug": "ai-ml",
      "points": [
        {
          "date": "2026-03-30",
          "ranking": 3,
          "github_score": 0.0,
          "so_score": 0.0,
          "reddit_score": 100.0,
          "trend_score": 25.0,
          "fuentes": 1,
          "available_source_codes": [
            "RD"
          ]
        },
        {
          "date": "2026-04-06",
          "ranking": 3,
          "github_score": 0.0,
          "so_score": 0.0,
          "reddit_score": 100.0,
          "trend_score": 25.0,
          "fuentes": 1,
          "available_source_codes": [
            "RD"
          ]
        }
      ]
    },
    {
      "tecnologia": "JavaScript",
      "slug": "javascript",
      "points": [
        {
          "date": "2026-03-30",
          "ranking": 4,
          "github_score": 19.42,
          "so_score": 41.79,
          "reddit_score": 0.0,
          "trend_score": 22.39,
          "fuentes": 2,
          "available_source_codes": [
            "GH",
            "SO"
          ]
        },
        {
          "date": "2026-04-06",
          "ranking": 4,
          "github_score": 19.54,
          "so_score": 41.5,
          "reddit_score": 0.0,
          "trend_score": 22.34,
          "fuentes": 2,
          "available_source_codes": [
            "GH",
            "SO"
          ]
        }
      ]
    },
    {
      "tecnologia": "Java",
      "slug": "java",
      "points": [
        {
          "date": "2026-03-30",
          "ranking": 5,
          "github_score": 2.27,
          "so_score": 41.76,
          "reddit_score": 0.0,
          "trend_score": 15.52,
          "fuentes": 2,
          "available_source_codes": [
            "GH",
            "SO"
          ]
        },
        {
          "date": "2026-04-06",
          "ranking": 5,
          "github_score": 2.28,
          "so_score": 41.42,
          "reddit_score": 0.0,
          "trend_score": 15.41,
          "fuentes": 2,
          "available_source_codes": [
            "GH",
            "SO"
          ]
        }
      ]
    },
    {
      "tecnologia": "C#",
      "slug": "c-sharp",
      "points": [
        {
          "date": "2026-03-30",
          "ranking": 6,
          "github_score": 1.62,
          "so_score": 40.66,
          "reddit_score": 0.0,
          "trend_score": 14.88,
          "fuentes": 2,
          "available_source_codes": [
            "GH",
            "SO"
          ]
        },
        {
          "date": "2026-04-06",
          "ranking": 6,
          "github_score": 1.95,
          "so_score": 40.7,
          "reddit_score": 0.0,
          "trend_score": 15.02,
          "fuentes": 2,
          "available_source_codes": [
            "GH",
            "SO"
          ]
        }
      ]
    },
    {
      "tecnologia": "C++",
      "slug": "c-plus-plus",
      "points": [
        {
          "date": "2026-03-30",
          "ranking": 7,
          "github_score": 4.53,
          "so_score": 35.3,
          "reddit_score": 0.0,
          "trend_score": 14.17,
          "fuentes": 2,
          "available_source_codes": [
            "GH",
            "SO"
          ]
        },
        {
          "date": "2026-04-06",
          "ranking": 7,
          "github_score": 4.89,
          "so_score": 35.69,
          "reddit_score": 0.0,
          "trend_score": 14.45,
          "fuentes": 2,
          "available_source_codes": [
            "GH",
            "SO"
          ]
        }
      ]
    },
    {
      "tecnologia": "Performance",
      "slug": "performance",
      "points": [
        {
          "date": "2026-03-30",
          "ranking": 9,
          "github_score": 0.0,
          "so_score": 0.0,
          "reddit_score": 26.32,
          "trend_score": 6.58,
          "fuentes": 1,
          "available_source_codes": [
            "RD"
          ]
        },
        {
          "date": "2026-04-06",
          "ranking": 8,
          "github_score": 0.0,
          "so_score": 0.0,
          "reddit_score": 32.85,
          "trend_score": 8.21,
          "fuentes": 1,
          "available_source_codes": [
            "RD"
          ]
        }
      ]
    },
    {
      "tecnologia": "Go",
      "slug": "go",
      "points": [
        {
          "date": "2026-03-30",
          "ranking": 8,
          "github_score": 15.21,
          "so_score": 2.47,
          "reddit_score": 0.0,
          "trend_score": 6.95,
          "fuentes": 2,
          "available_source_codes": [
            "GH",
            "SO"
          ]
        },
        {
          "date": "2026-04-06",
          "ranking": 9,
          "github_score": 16.29,
          "so_score": 2.51,
          "reddit_score": 0.0,
          "trend_score": 7.39,
          "fuentes": 2,
          "available_source_codes": [
            "GH",
            "SO"
          ]
        }
      ]
    },
    {
      "tecnologia": "Security",
      "slug": "security",
      "points": [
        {
          "date": "2026-03-30",
          "ranking": 10,
          "github_score": 0.0,
          "so_score": 0.0,
          "reddit_score": 25.0,
          "trend_score": 6.25,
          "fuentes": 1,
          "available_source_codes": [
            "RD"
          ]
        },
        {
          "date": "2026-04-06",
          "ranking": 10,
          "github_score": 0.0,
          "so_score": 0.0,
          "reddit_score": 26.28,
          "trend_score": 6.57,
          "fuentes": 1,
          "available_source_codes": [
            "RD"
          ]
        }
      ]
    },
    {
      "tecnologia": "Rust",
      "slug": "rust",
      "points": [
        {
          "date": "2026-03-30",
          "ranking": 13,
          "github_score": 11.65,
          "so_score": 0.0,
          "reddit_score": 0.0,
          "trend_score": 4.66,
          "fuentes": 1,
          "available_source_codes": [
            "GH"
          ]
        },
        {
          "date": "2026-04-06",
          "ranking": 11,
          "github_score": 13.36,
          "so_score": 0.0,
          "reddit_score": 0.0,
          "trend_score": 5.34,
          "fuentes": 1,
          "available_source_codes": [
            "GH"
          ]
        }
      ]
    },
    {
      "tecnologia": "DevOps",
      "slug": "devops",
      "points": [
        {
          "date": "2026-03-30",
          "ranking": 11,
          "github_score": 0.0,
          "so_score": 0.0,
          "reddit_score": 21.71,
          "trend_score": 5.43,
          "fuentes": 1,
          "available_source_codes": [
            "RD"
          ]
        },
        {
          "date": "2026-04-06",
          "ranking": 12,
          "github_score": 0.0,
          "so_score": 0.0,
          "reddit_score": 20.44,
          "trend_score": 5.11,
          "fuentes": 1,
          "available_source_codes": [
            "RD"
          ]
        }
      ]
    },
    {
      "tecnologia": "Kotlin",
      "slug": "kotlin",
      "points": [
        {
          "date": "2026-03-30",
          "ranking": 12,
          "github_score": 2.59,
          "so_score": 11.22,
          "reddit_score": 0.0,
          "trend_score": 4.96,
          "fuentes": 2,
          "available_source_codes": [
            "GH",
            "SO"
          ]
        },
        {
          "date": "2026-04-06",
          "ranking": 13,
          "github_score": 2.61,
          "so_score": 11.19,
          "reddit_score": 0.0,
          "trend_score": 4.96,
          "fuentes": 2,
          "available_source_codes": [
            "GH",
            "SO"
          ]
        }
      ]
    },
    {
      "tecnologia": "Cloud",
      "slug": "cloud",
      "points": [
        {
          "date": "2026-03-30",
          "ranking": 16,
          "github_score": 0.0,
          "so_score": 0.0,
          "reddit_score": 15.79,
          "trend_score": 3.95,
          "fuentes": 1,
          "available_source_codes": [
            "RD"
          ]
        },
        {
          "date": "2026-04-06",
          "ranking": 14,
          "github_score": 0.0,
          "so_score": 0.0,
          "reddit_score": 18.98,
          "trend_score": 4.75,
          "fuentes": 1,
          "available_source_codes": [
            "RD"
          ]
        }
      ]
    },
    {
      "tecnologia": "Shell",
      "slug": "shell",
      "points": [
        {
          "date": "2026-03-30",
          "ranking": 15,
          "github_score": 10.36,
          "so_score": 0.0,
          "reddit_score": 0.0,
          "trend_score": 4.14,
          "fuentes": 1,
          "available_source_codes": [
            "GH"
          ]
        },
        {
          "date": "2026-04-06",
          "ranking": 15,
          "github_score": 11.73,
          "so_score": 0.0,
          "reddit_score": 0.0,
          "trend_score": 4.69,
          "fuentes": 1,
          "available_source_codes": [
            "GH"
          ]
        }
      ]
    },
    {
      "tecnologia": "PHP",
      "slug": "php",
      "points": [
        {
          "date": "2026-03-30",
          "ranking": 14,
          "github_score": 0.0,
          "so_score": 12.46,
          "reddit_score": 0.0,
          "trend_score": 4.36,
          "fuentes": 1,
          "available_source_codes": [
            "SO"
          ]
        },
        {
          "date": "2026-04-06",
          "ranking": 16,
          "github_score": 0.0,
          "so_score": 12.57,
          "reddit_score": 0.0,
          "trend_score": 4.4,
          "fuentes": 1,
          "available_source_codes": [
            "SO"
          ]
        }
      ]
    },
    {
      "tecnologia": "Testing",
      "slug": "testing",
      "points": [
        {
          "date": "2026-03-30",
          "ranking": 17,
          "github_score": 0.0,
          "so_score": 0.0,
          "reddit_score": 8.55,
          "trend_score": 2.14,
          "fuentes": 1,
          "available_source_codes": [
            "RD"
          ]
        },
        {
          "date": "2026-04-06",
          "ranking": 17,
          "github_score": 0.0,
          "so_score": 0.0,
          "reddit_score": 11.68,
          "trend_score": 2.92,
          "fuentes": 1,
          "available_source_codes": [
            "RD"
          ]
        }
      ]
    },
    {
      "tecnologia": "Html",
      "slug": "html",
      "points": [
        {
          "date": "2026-03-30",
          "ranking": 19,
          "github_score": 4.21,
          "so_score": 0.0,
          "reddit_score": 0.0,
          "trend_score": 1.68,
          "fuentes": 1,
          "available_source_codes": [
            "GH"
          ]
        },
        {
          "date": "2026-04-06",
          "ranking": 18,
          "github_score": 5.21,
          "so_score": 0.0,
          "reddit_score": 0.0,
          "trend_score": 2.08,
          "fuentes": 1,
          "available_source_codes": [
            "GH"
          ]
        }
      ]
    },
    {
      "tecnologia": "Swift",
      "slug": "swift",
      "points": [
        {
          "date": "2026-03-30",
          "ranking": 18,
          "github_score": 4.85,
          "so_score": 0.0,
          "reddit_score": 0.0,
          "trend_score": 1.94,
          "fuentes": 1,
          "available_source_codes": [
            "GH"
          ]
        },
        {
          "date": "2026-04-06",
          "ranking": 19,
          "github_score": 5.21,
          "so_score": 0.0,
          "reddit_score": 0.0,
          "trend_score": 2.08,
          "fuentes": 1,
          "available_source_codes": [
            "GH"
          ]
        }
      ]
    },
    {
      "tecnologia": "Jupyter Notebook",
      "slug": "jupyter-notebook",
      "points": [
        {
          "date": "2026-03-30",
          "ranking": 20,
          "github_score": 3.56,
          "so_score": 0.0,
          "reddit_score": 0.0,
          "trend_score": 1.42,
          "fuentes": 1,
          "available_source_codes": [
            "GH"
          ]
        },
        {
          "date": "2026-04-06",
          "ranking": 20,
          "github_score": 2.93,
          "so_score": 0.0,
          "reddit_score": 0.0,
          "trend_score": 1.17,
          "fuentes": 1,
          "available_source_codes": [
            "GH"
          ]
        }
      ]
    },
    {
      "tecnologia": "C",
      "slug": "c",
      "points": [
        {
          "date": "2026-03-30",
          "ranking": 21,
          "github_score": 2.27,
          "so_score": 0.0,
          "reddit_score": 0.0,
          "trend_score": 0.91,
          "fuentes": 1,
          "available_source_codes": [
            "GH"
          ]
        },
        {
          "date": "2026-04-06",
          "ranking": 21,
          "github_score": 2.61,
          "so_score": 0.0,
          "reddit_score": 0.0,
          "trend_score": 1.04,
          "fuentes": 1,
          "available_source_codes": [
            "GH"
          ]
        }
      ]
    },
    {
      "tecnologia": "Microservices",
      "slug": "microservices",
      "points": [
        {
          "date": "2026-03-30",
          "ranking": 22,
          "github_score": 0.0,
          "so_score": 0.0,
          "reddit_score": 1.97,
          "trend_score": 0.49,
          "fuentes": 1,
          "available_source_codes": [
            "RD"
          ]
        }
      ]
    }
  ],
  "latest_snapshot_date": "2026-04-06"
}