{
  "generated_at_utc": "2026-07-06T12:24:55Z",
  "dataset": "so_volumen_preguntas",
  "source_mode": "history",
  "snapshot_count": 2,
  "latest_snapshot_date": "2026-07-06",
  "previous_snapshot_date": "2026-06-29",
  "has_historical_comparison": true,
  "item_count": 10,
  "summary": {
    "leader": {
      "lenguaje": "python",
      "preguntas": 5995,
      "preguntas_prev": 6192,
      "delta_preguntas": -197,
      "growth_pct": -3.18,
      "trend_direction": "cayendo",
      "share_pct": 31.12
    },
    "highest_growth": {
      "lenguaje": "ruby",
      "preguntas": 99,
      "preguntas_prev": 98,
      "delta_preguntas": 1,
      "growth_pct": 1.02,
      "trend_direction": "creciendo",
      "share_pct": 0.51
    },
    "largest_drop": {
      "lenguaje": "python",
      "preguntas": 5995,
      "preguntas_prev": 6192,
      "delta_preguntas": -197,
      "growth_pct": -3.18,
      "trend_direction": "cayendo",
      "share_pct": 31.12
    },
    "total_questions": 19267
  },
  "latest_items": [
    {
      "lenguaje": "python",
      "preguntas": 5995,
      "preguntas_prev": 6192,
      "delta_preguntas": -197,
      "growth_pct": -3.18,
      "trend_direction": "cayendo",
      "share_pct": 31.12
    },
    {
      "lenguaje": "c#",
      "preguntas": 2645,
      "preguntas_prev": 2707,
      "delta_preguntas": -62,
      "growth_pct": -2.29,
      "trend_direction": "cayendo",
      "share_pct": 13.73
    },
    {
      "lenguaje": "java",
      "preguntas": 2613,
      "preguntas_prev": 2688,
      "delta_preguntas": -75,
      "growth_pct": -2.79,
      "trend_direction": "cayendo",
      "share_pct": 13.56
    },
    {
      "lenguaje": "javascript",
      "preguntas": 2543,
      "preguntas_prev": 2622,
      "delta_preguntas": -79,
      "growth_pct": -3.01,
      "trend_direction": "cayendo",
      "share_pct": 13.2
    },
    {
      "lenguaje": "c++",
      "preguntas": 2427,
      "preguntas_prev": 2499,
      "delta_preguntas": -72,
      "growth_pct": -2.88,
      "trend_direction": "cayendo",
      "share_pct": 12.6
    },
    {
      "lenguaje": "typescript",
      "preguntas": 1118,
      "preguntas_prev": 1158,
      "delta_preguntas": -40,
      "growth_pct": -3.45,
      "trend_direction": "cayendo",
      "share_pct": 5.8
    },
    {
      "lenguaje": "php",
      "preguntas": 819,
      "preguntas_prev": 847,
      "delta_preguntas": -28,
      "growth_pct": -3.31,
      "trend_direction": "cayendo",
      "share_pct": 4.25
    },
    {
      "lenguaje": "kotlin",
      "preguntas": 745,
      "preguntas_prev": 773,
      "delta_preguntas": -28,
      "growth_pct": -3.62,
      "trend_direction": "cayendo",
      "share_pct": 3.87
    },
    {
      "lenguaje": "go",
      "preguntas": 263,
      "preguntas_prev": 273,
      "delta_preguntas": -10,
      "growth_pct": -3.66,
      "trend_direction": "cayendo",
      "share_pct": 1.37
    },
    {
      "lenguaje": "ruby",
      "preguntas": 99,
      "preguntas_prev": 98,
      "delta_preguntas": 1,
      "growth_pct": 1.02,
      "trend_direction": "creciendo",
      "share_pct": 0.51
    }
  ],
  "snapshots": [
    {
      "date": "2026-06-29",
      "path": "datos/history/so_volumen/year=2026/month=06/day=29/so_volumen_preguntas.csv",
      "source_type": "history",
      "row_count": 10,
      "item_count": 10,
      "total_questions": 19857,
      "items": [
        {
          "lenguaje": "python",
          "preguntas": 6192,
          "share_pct": 31.18
        },
        {
          "lenguaje": "c#",
          "preguntas": 2707,
          "share_pct": 13.63
        },
        {
          "lenguaje": "java",
          "preguntas": 2688,
          "share_pct": 13.54
        },
        {
          "lenguaje": "javascript",
          "preguntas": 2622,
          "share_pct": 13.2
        },
        {
          "lenguaje": "c++",
          "preguntas": 2499,
          "share_pct": 12.58
        },
        {
          "lenguaje": "typescript",
          "preguntas": 1158,
          "share_pct": 5.83
        },
        {
          "lenguaje": "php",
          "preguntas": 847,
          "share_pct": 4.27
        },
        {
          "lenguaje": "kotlin",
          "preguntas": 773,
          "share_pct": 3.89
        },
        {
          "lenguaje": "go",
          "preguntas": 273,
          "share_pct": 1.37
        },
        {
          "lenguaje": "ruby",
          "preguntas": 98,
          "share_pct": 0.49
        }
      ]
    },
    {
      "date": "2026-07-06",
      "path": "datos/history/so_volumen/year=2026/month=07/day=06/so_volumen_preguntas.csv",
      "source_type": "history",
      "row_count": 10,
      "item_count": 10,
      "total_questions": 19267,
      "items": [
        {
          "lenguaje": "python",
          "preguntas": 5995,
          "share_pct": 31.12
        },
        {
          "lenguaje": "c#",
          "preguntas": 2645,
          "share_pct": 13.73
        },
        {
          "lenguaje": "java",
          "preguntas": 2613,
          "share_pct": 13.56
        },
        {
          "lenguaje": "javascript",
          "preguntas": 2543,
          "share_pct": 13.2
        },
        {
          "lenguaje": "c++",
          "preguntas": 2427,
          "share_pct": 12.6
        },
        {
          "lenguaje": "typescript",
          "preguntas": 1118,
          "share_pct": 5.8
        },
        {
          "lenguaje": "php",
          "preguntas": 819,
          "share_pct": 4.25
        },
        {
          "lenguaje": "kotlin",
          "preguntas": 745,
          "share_pct": 3.87
        },
        {
          "lenguaje": "go",
          "preguntas": 263,
          "share_pct": 1.37
        },
        {
          "lenguaje": "ruby",
          "preguntas": 99,
          "share_pct": 0.51
        }
      ]
    }
  ]
}